china_dictatorship/README.adoc
china_dictatorship/README.html
china_dictatorship/__init__.py
china_dictatorship-0.0.37.data/scripts/china-dictatorship.py
china_dictatorship-0.0.37.dist-info/LICENSE
china_dictatorship-0.0.37.dist-info/METADATA
china_dictatorship-0.0.37.dist-info/WHEEL
china_dictatorship-0.0.37.dist-info/top_level.txt
china_dictatorship-0.0.37.dist-info/RECORD
