Metadata-Version: 2.1
Name: china-dictatorship
Version: 0.0.37
Summary: 2018新疆改造中心，1989六四事件，1999法轮功 ，2019 996.ICU, 2018包子露宪，2015 710律师劫，2015巴拿马文件 邓家贵，2017低端人口，2008西藏骚乱
Home-page: https://github.com/cirosantilli/china-dictatorship
Author: Ciro Santilli
Author-email: ciro.santilli.contact@gmail.com
License: UNKNOWN
Platform: UNKNOWN
